demetriocalc/__init__.py
demetriocalc/demetriocalc.py
demetriocalc-0.1.0.dist-info/METADATA
demetriocalc-0.1.0.dist-info/WHEEL
demetriocalc-0.1.0.dist-info/top_level.txt
demetriocalc-0.1.0.dist-info/RECORD
