Metadata-Version: 2.1
Name: demetriocalc
Version: 0.1.0
Summary: Uma calculadora simples em Python.
Author-email: Demetrio <demetrio.luna@academico.edu.ifpb.br>
License: MIT
Classifier: Programming Language :: Python :: 3
Classifier: Operating System :: OS Independent
Requires-Python: >=3.6
